open_qlik_sdk/__init__.py
open_qlik_sdk/_version.py
open_qlik_sdk/auth.py
open_qlik_sdk/auth_type.py
open_qlik_sdk/config.py
open_qlik_sdk/errors.py
open_qlik_sdk/generate_signed_token.py
open_qlik_sdk/listable.py
open_qlik_sdk/oauth_utils.py
open_qlik_sdk/qlik.py
open_qlik_sdk/rest.py
open_qlik_sdk/rpc.py
open_qlik_sdk/utils.py
open_qlik_sdk/apis/Api_Keys.py
open_qlik_sdk/apis/Apps.py
open_qlik_sdk/apis/Audits.py
open_qlik_sdk/apis/Automations.py
open_qlik_sdk/apis/Brands.py
open_qlik_sdk/apis/Collections.py
open_qlik_sdk/apis/Csp_Origins.py
open_qlik_sdk/apis/Data_Files.py
open_qlik_sdk/apis/Extensions.py
open_qlik_sdk/apis/Groups.py
open_qlik_sdk/apis/Identity_Providers.py
open_qlik_sdk/apis/Items.py
open_qlik_sdk/apis/Licenses.py
open_qlik_sdk/apis/Notes.py
open_qlik_sdk/apis/Oauth_Tokens.py
open_qlik_sdk/apis/Qix.py
open_qlik_sdk/apis/Questions.py
open_qlik_sdk/apis/Quotas.py
open_qlik_sdk/apis/Reload_Tasks.py
open_qlik_sdk/apis/Reloads.py
open_qlik_sdk/apis/Roles.py
open_qlik_sdk/apis/Spaces.py
open_qlik_sdk/apis/Tenants.py
open_qlik_sdk/apis/Themes.py
open_qlik_sdk/apis/Transports.py
open_qlik_sdk/apis/Users.py
open_qlik_sdk/apis/Web_Integrations.py
open_qlik_sdk/apis/Webhooks.py
open_qlik_sdk/apis/__init__.py
open_qlik_sdk/interceptors/__init__.py
open_qlik_sdk/interceptors/retry_response.py
open_qlik_sdk/interceptors/types.py
open_qlik_sdk-1.0.0.dist-info/licenses/LICENSE
open_qlik_sdk-1.0.0.dist-info/METADATA
open_qlik_sdk-1.0.0.dist-info/WHEEL
open_qlik_sdk-1.0.0.dist-info/top_level.txt
open_qlik_sdk-1.0.0.dist-info/RECORD
