Metadata-Version: 2.4
Name: open-qlik-sdk
Version: 1.0.0
Summary: Software Development Kit for Qlik Cloud
Author-email: Vincent Chantreau <contact@vincentchantreau.fr>
Maintainer-email: Vincent Chantreau <contact@vincentchantreau.fr>
License: MIT License
Requires-Python: >=3.11
License-File: LICENSE
Requires-Dist: requests==2.31.0
Requires-Dist: websocket-client==1.8.0
Requires-Dist: PyJWT==2.8.0
Dynamic: license-file
